PySSH/ShellScriptHandeler.py
PySSH/__init__.py
ShellScriptHandeler/ShellScriptHandeler.py
ShellScriptHandeler/__init__.py
ShellScriptHandeler-0.0.6.dist-info/METADATA
ShellScriptHandeler-0.0.6.dist-info/WHEEL
ShellScriptHandeler-0.0.6.dist-info/top_level.txt
ShellScriptHandeler-0.0.6.dist-info/RECORD
