Metadata-Version: 2.1
Name: ShellScriptHandeler
Version: 0.0.6
Summary: Opens and runs Shellscripts
Home-page: UNKNOWN
Author: Teer2008
Author-email: <henryzimmermann4@gmail.com>
License: UNKNOWN
Keywords: python,shellscript,sh,.sh,run sh,open
Platform: UNKNOWN
Classifier: Development Status :: 1 - Planning
Classifier: Intended Audience :: Developers
Classifier: Programming Language :: Python :: 3
Classifier: Operating System :: Unix
Classifier: Operating System :: MacOS :: MacOS X
Classifier: Operating System :: Microsoft :: Windows
